README.md
setup.py
linkedin_driver/__init__.py
linkedin_driver/api.py
linkedin_driver/test.py
linkedin_driver/utils.py
linkedin_driver.egg-info/PKG-INFO
linkedin_driver.egg-info/SOURCES.txt
linkedin_driver.egg-info/dependency_links.txt
linkedin_driver.egg-info/not-zip-safe
linkedin_driver.egg-info/requires.txt
linkedin_driver.egg-info/top_level.txt