Metadata-Version: 2.1
Name: linkedin-driver
Version: 0.1.7.1
Summary: Linkedin driver.
Home-page: https://github.com/sujitech/linkedin_driver
Author: Mindey
Author-email: mindey@qq.com
License: ASK FOR PERMISSIONS
Platform: UNKNOWN
Provides-Extra: test
